LICENSE
MANIFEST.in
README.rst
setup.py
tests/test_basic.py
tui_editor/__init__.py
tui_editor/_setup_info_generated.py
tui_editor/tty_helpers.py
tui_editor/tui_editor.py
tui_editor.egg-info/PKG-INFO
tui_editor.egg-info/SOURCES.txt
tui_editor.egg-info/dependency_links.txt
tui_editor.egg-info/top_level.txt