Metadata-Version: 2.1
Name: tui-editor
Version: 1.20240813.3421
Summary: Simple Python terminal (TUI) multi-line editor
Home-page: https://github.com/albertz/py-tui-editor
Author: Albert Zeyer
Author-email: albzey@gmail.com
License: MIT License
Classifier: Development Status :: 4 - Beta
Classifier: Intended Audience :: Developers
Classifier: Intended Audience :: Education
Classifier: Intended Audience :: Science/Research
Classifier: License :: OSI Approved :: MIT License
Classifier: Operating System :: MacOS :: MacOS X
Classifier: Operating System :: POSIX
Classifier: Operating System :: Unix
Classifier: Programming Language :: Python
Classifier: Topic :: Software Development :: Libraries
Classifier: Topic :: Software Development :: Libraries :: Python Modules
Classifier: Topic :: Software Development :: User Interfaces
Classifier: Topic :: System :: Shells
Classifier: Topic :: Terminals
Classifier: Topic :: Text Editors
License-File: LICENSE
